mlcode/__init__.py
mlcode/program_logic.py
mlcode/programs/program1.txt
mlcode/programs/program2.txt
mlcode/programs/program3.1.txt
mlcode/programs/program3.2.txt
mlcode/programs/program4.txt
mlcode/programs/program5.txt
mlcode/programs/program6.txt
mlcode/programs/program7.txt
mlcode-1.2.0.dist-info/METADATA
mlcode-1.2.0.dist-info/WHEEL
mlcode-1.2.0.dist-info/top_level.txt
mlcode-1.2.0.dist-info/RECORD
